<?xml version='1.0' encoding='UTF-8'?>
<guiaRemision version="1.1.0" id="comprobante"><infoTributaria><ambiente>1</ambiente><tipoEmision>1</tipoEmision><razonSocial>CABLESPEED CIA LTDA</razonSocial><nombreComercial>SALAZAR AGUILAR LUIS GUILLERMO</nombreComercial><ruc>1091725041001</ruc><claveAcceso>0308202106109172504100110010010000009322825655017</claveAcceso><codDoc>06</codDoc><estab>001</estab><ptoEmi>001</ptoEmi><secuencial>000000932</secuencial><dirMatriz>SAN MARCOS DECIMA QUINTA SN Y LUIS ESPINOZA</dirMatriz></infoTributaria><infoGuiaRemision><dirEstablecimiento>SAN MARCOS DECIMA QUINTA SN Y LUIS ESPINOZA</dirEstablecimiento><dirPartida>SAN MARCOS DECIMA QUINTA SN Y LUIS ESPINOZA</dirPartida><razonSocialTransportista>BRYAN MUÑOZ</razonSocialTransportista><tipoIdentificacionTransportista>05</tipoIdentificacionTransportista><rucTransportista>0750698789</rucTransportista><obligadoContabilidad>NO</obligadoContabilidad><fechaIniTransporte>03/08/2021</fechaIniTransporte><fechaFinTransporte>03/08/2021</fechaFinTransporte><placa>OBA1822</placa></infoGuiaRemision><destinatarios><destinatario><identificacionDestinatario>0703623652001</identificacionDestinatario><razonSocialDestinatario>MARICH VIVAR HOOVER ANDRES</razonSocialDestinatario><dirDestinatario>TENGUEL SITIO EL CONCHERO S/N</dirDestinatario><motivoTraslado>ENTREGA</motivoTraslado><detalles><detalle><codigoInterno>1</codigoInterno><codigoAdicional>1</codigoAdicional><descripcion>GAVETAS CONICAS</descripcion><cantidad>460</cantidad></detalle><detalle><codigoInterno>2</codigoInterno><codigoAdicional>2</codigoAdicional><descripcion>GAVETAS CALADAS</descripcion><cantidad>60</cantidad></detalle><detalle><codigoInterno>5</codigoInterno><codigoAdicional>5</codigoAdicional><descripcion>BINES</descripcion><cantidad>0</cantidad></detalle><detalle><codigoInterno>6</codigoInterno><codigoAdicional>6</codigoAdicional><descripcion>OTROS</descripcion><cantidad>0</cantidad></detalle><detalle><codigoInterno>7</codigoInterno><codigoAdicional>7</codigoAdicional><descripcion>SACOS C/HIELO</descripcion><cantidad>450</cantidad></detalle><detalle><codigoInterno>8</codigoInterno><codigoAdicional>8</codigoAdicional><descripcion>SACOS METABISULFITO</descripcion><cantidad>0</cantidad></detalle><detalle><codigoInterno>9</codigoInterno><codigoAdicional>9</codigoAdicional><descripcion>SACOS SAL</descripcion><cantidad>0</cantidad></detalle></detalles></destinatario></destinatarios><infoAdicional><campoAdicional nombre="Agente de Retención">No.Resolución: </campoAdicional></infoAdicional></guiaRemision>